sanitycheckhaha/ParseStealth.py
sanitycheckhaha/__init__.py
sanitycheckhaha/sanitycheckhaha.py
sanitycheckhaha-0.0.3.dist-info/entry_points.txt
sanitycheckhaha-0.0.3.dist-info/LICENSE
sanitycheckhaha-0.0.3.dist-info/WHEEL
sanitycheckhaha-0.0.3.dist-info/METADATA
sanitycheckhaha-0.0.3.dist-info/RECORD
