Metadata-Version: 2.1
Name: sanitycheckhaha
Version: 0.0.3
Summary: Test of a commandline feature python package
Home-page: https://github.com/tagaw/sanitycheckhaha
License: GPL-3
Keywords: example
Author: Tyler Gaw
Maintainer: Tyler Gaw
Classifier: License :: Other/Proprietary License
Classifier: Programming Language :: Python :: 2
Classifier: Programming Language :: Python :: 2.7
Classifier: Programming Language :: Python :: 3
Classifier: Programming Language :: Python :: 3.10
Classifier: Programming Language :: Python :: 3.4
Classifier: Programming Language :: Python :: 3.5
Classifier: Programming Language :: Python :: 3.6
Classifier: Programming Language :: Python :: 3.7
Classifier: Programming Language :: Python :: 3.8
Classifier: Programming Language :: Python :: 3.9
Project-URL: Repository, https://github.com/tagaw/sanitycheckhaha
